pyenumerable/__init__.py
pyenumerable/constructors.py
pyenumerable/typing_utility.py
pyenumerable/implementations/__init__.py
pyenumerable/implementations/pure_python.py
pyenumerable/implementations/utils.py
pyenumerable/protocol/__init__.py
pyenumerable/protocol/_associable.py
pyenumerable/protocol/_enumerable.py
pyenumerable/protocol/_supports_aggregate.py
pyenumerable/protocol/_supports_all.py
pyenumerable/protocol/_supports_any.py
pyenumerable/protocol/_supports_append.py
pyenumerable/protocol/_supports_average.py
pyenumerable/protocol/_supports_chunk.py
pyenumerable/protocol/_supports_concat.py
pyenumerable/protocol/_supports_contains.py
pyenumerable/protocol/_supports_count.py
pyenumerable/protocol/_supports_distinct.py
pyenumerable/protocol/_supports_except.py
pyenumerable/protocol/_supports_group_by.py
pyenumerable/protocol/_supports_group_join.py
pyenumerable/protocol/_supports_intersect.py
pyenumerable/protocol/_supports_join.py
pyenumerable/protocol/_supports_max.py
pyenumerable/protocol/_supports_min.py
pyenumerable/protocol/_supports_of_type.py
pyenumerable/protocol/_supports_order.py
pyenumerable/protocol/_supports_prepend.py
pyenumerable/protocol/_supports_reverse.py
pyenumerable/protocol/_supports_select.py
pyenumerable/protocol/_supports_sequence_equal.py
pyenumerable/protocol/_supports_single.py
pyenumerable/protocol/_supports_skip.py
pyenumerable/protocol/_supports_sum.py
pyenumerable/protocol/_supports_take.py
pyenumerable/protocol/_supports_union.py
pyenumerable/protocol/_supports_where.py
pyenumerable/protocol/_supports_zip.py
pyenumerable-2.0.1.dist-info/licenses/license.txt
pyenumerable-2.0.1.dist-info/METADATA
pyenumerable-2.0.1.dist-info/WHEEL
pyenumerable-2.0.1.dist-info/top_level.txt
pyenumerable-2.0.1.dist-info/RECORD
