Metadata-Version: 2.4
Name: pyenumerable
Version: 2.0.1
Summary: Implementation of .net's IEnumerable interface in python W/ support for generics.
Author-email: AmirHossein Ahmadi <amirthehossein@gmail.com>
License-Expression: WTFPL
Project-URL: Homepage, https://github.com/amirongit/PyEnumerable/
Project-URL: Source, https://github.com/amirongit/PyEnumerable/
Project-URL: Documentation, https://github.com/amirongit/PyEnumerable/blob/master/documentation.md
Project-URL: Repository, https://github.com/amirongit/PyEnumerable.git
Requires-Python: >=3.13
License-File: license.txt
Dynamic: license-file
